vss_ctx_rag/plugins/nat/__init__.py
vss_ctx_rag/plugins/nat/register_in.py
vss_ctx_rag/plugins/nat/register_ret.py
vss_ctx_rag/plugins/nat/utils.py
vss_ctx_rag/plugins/nat/workflow/__init__.py
vss_ctx_rag/plugins/nat/workflow/register_tool_call_workflow.py
vss_ctx_rag/plugins/nat/workflow/tool_call_workflow.py
vss_ctx_rag_nat-1.0.1.dist-info/METADATA
vss_ctx_rag_nat-1.0.1.dist-info/WHEEL
vss_ctx_rag_nat-1.0.1.dist-info/entry_points.txt
vss_ctx_rag_nat-1.0.1.dist-info/top_level.txt
vss_ctx_rag_nat-1.0.1.dist-info/RECORD
