Metadata-Version: 2.4
Name: vss_ctx_rag_nat
Version: 1.0.1
Summary: Subpackage for NAT Integration in vss_ctx_rag
Requires-Python: >=3.11
Requires-Dist: vss_ctx_rag
